{
  "swagger": "2.0",
  "info": {
    "title": "",
    "version": ""
  },
  "schemes": [
    "http",
    "https"
  ],
  "consumes": [
    "application/json"
  ],
  "produces": [
    "application/json"
  ],
  "paths": {
    "/v1/auth/check": {
      "get": {
        "summary": "Check user is exist",
        "operationId": "CheckUser",
        "responses": {
          "200": {
            "description": "A successful response.",
            "schema": {
              "allOf": [
                {
                  "$ref": "#/definitions/Response"
                },
                {
                  "type": "object",
                  "properties": {
                    "data": {
                      "$ref": "#/definitions/CheckUserResponse"
                    }
                  }
                }
              ]
            }
          }
        },
        "parameters": [
          {
            "name": "email",
            "in": "query",
            "required": true,
            "type": "string"
          }
        ],
        "tags": [
          "ppanel/auth"
        ]
      }
    },
    "/v1/auth/login": {
      "post": {
        "summary": "User login",
        "operationId": "UserLogin",
        "responses": {
          "200": {
            "description": "A successful response.",
            "schema": {
              "allOf": [
                {
                  "$ref": "#/definitions/Response"
                },
                {
                  "type": "object",
                  "properties": {
                    "data": {
                      "$ref": "#/definitions/LoginResponse"
                    }
                  }
                }
              ]
            }
          }
        },
        "parameters": [
          {
            "name": "X-Original-Forwarded-For",
            "in": "header",
            "required": true,
            "type": "string"
          },
          {
            "name": "body",
            "description": "User login request",
            "in": "body",
            "required": true,
            "schema": {
              "$ref": "#/definitions/UserLoginRequest"
            }
          }
        ],
        "tags": [
          "ppanel/auth"
        ]
      }
    },
    "/v1/auth/register": {
      "post": {
        "summary": "User register",
        "operationId": "UserRegister",
        "responses": {
          "200": {
            "description": "A successful response.",
            "schema": {
              "allOf": [
                {
                  "$ref": "#/definitions/Response"
                },
                {
                  "type": "object",
                  "properties": {
                    "data": {
                      "$ref": "#/definitions/LoginResponse"
                    }
                  }
                }
              ]
            }
          }
        },
        "parameters": [
          {
            "name": "X-Original-Forwarded-For",
            "in": "header",
            "required": true,
            "type": "string"
          },
          {
            "name": "body",
            "description": "User login response",
            "in": "body",
            "required": true,
            "schema": {
              "$ref": "#/definitions/UserRegisterRequest"
            }
          }
        ],
        "tags": [
          "ppanel/auth"
        ]
      }
    },
    "/v1/auth/reset": {
      "post": {
        "summary": "Reset password",
        "operationId": "ResetPassword",
        "responses": {
          "200": {
            "description": "A successful response.",
            "schema": {
              "allOf": [
                {
                  "$ref": "#/definitions/Response"
                },
                {
                  "type": "object",
                  "properties": {
                    "data": {
                      "$ref": "#/definitions/LoginResponse"
                    }
                  }
                }
              ]
            }
          }
        },
        "parameters": [
          {
            "name": "X-Original-Forwarded-For",
            "in": "header",
            "required": true,
            "type": "string"
          },
          {
            "name": "body",
            "description": "User login response",
            "in": "body",
            "required": true,
            "schema": {
              "$ref": "#/definitions/ResetPasswordRequest"
            }
          }
        ],
        "tags": [
          "ppanel/auth"
        ]
      }
    },
    "/v1/common/send_code": {
      "post": {
        "summary": "Get verification code",
        "operationId": "SendEmailCode",
        "responses": {
          "200": {
            "description": "A successful response.",
            "schema": {
              "allOf": [
                {
                  "$ref": "#/definitions/Response"
                },
                {
                  "type": "object",
                  "properties": {
                    "data": {
                      "$ref": "#/definitions/SendCodeResponse"
                    }
                  }
                }
              ]
            }
          }
        },
        "parameters": [
          {
            "name": "body",
            "description": "GetCodeRequest Get code request",
            "in": "body",
            "required": true,
            "schema": {
              "$ref": "#/definitions/SendCodeRequest"
            }
          }
        ],
        "tags": [
          "ppanel/common"
        ]
      }
    },
    "/v1/common/site/config": {
      "get": {
        "summary": "Get global config",
        "operationId": "GetGlobalConfig",
        "responses": {
          "200": {
            "description": "A successful response.",
            "schema": {
              "allOf": [
                {
                  "$ref": "#/definitions/Response"
                },
                {
                  "type": "object",
                  "properties": {
                    "data": {
                      "$ref": "#/definitions/GetGlobalConfigResponse"
                    }
                  }
                }
              ]
            }
          }
        },
        "tags": [
          "ppanel/common"
        ]
      }
    },
    "/v1/common/site/stat": {
      "get": {
        "summary": "Get stat",
        "operationId": "GetStat",
        "responses": {
          "200": {
            "description": "A successful response.",
            "schema": {
              "allOf": [
                {
                  "$ref": "#/definitions/Response"
                },
                {
                  "type": "object",
                  "properties": {
                    "data": {
                      "$ref": "#/definitions/GetStatResponse"
                    }
                  }
                }
              ]
            }
          }
        },
        "tags": [
          "ppanel/common"
        ]
      }
    },
    "/v1/common/site/subscribe": {
      "get": {
        "summary": "Get Subscription",
        "operationId": "GetSubscription",
        "responses": {
          "200": {
            "description": "A successful response.",
            "schema": {
              "allOf": [
                {
                  "$ref": "#/definitions/Response"
                },
                {
                  "type": "object",
                  "properties": {
                    "data": {
                      "$ref": "#/definitions/GetSubscriptionResponse"
                    }
                  }
                }
              ]
            }
          }
        },
        "tags": [
          "ppanel/common"
        ]
      }
    },
    "/v1/common/site/tos": {
      "get": {
        "summary": "Get Tos Content",
        "operationId": "GetTos",
        "responses": {
          "200": {
            "description": "A successful response.",
            "schema": {
              "allOf": [
                {
                  "$ref": "#/definitions/Response"
                },
                {
                  "type": "object",
                  "properties": {
                    "data": {
                      "$ref": "#/definitions/GetTosResponse"
                    }
                  }
                }
              ]
            }
          }
        },
        "tags": [
          "ppanel/common"
        ]
      }
    }
  },
  "definitions": {
    "Announcement": {
      "type": "object",
      "properties": {
        "id": {
          "type": "integer",
          "format": "int64"
        },
        "title": {
          "type": "string"
        },
        "content": {
          "type": "string"
        },
        "enable": {
          "type": "boolean",
          "format": "boolean"
        },
        "created_at": {
          "type": "integer",
          "format": "int64"
        },
        "updated_at": {
          "type": "integer",
          "format": "int64"
        }
      },
      "title": "Announcement",
      "required": [
        "id",
        "title",
        "content",
        "enable",
        "created_at",
        "updated_at"
      ]
    },
    "Application": {
      "type": "object",
      "properties": {
        "id": {
          "type": "integer",
          "format": "int64"
        },
        "name": {
          "type": "string"
        },
        "platform": {
          "type": "string"
        },
        "subscribe_type": {
          "type": "string"
        },
        "icon": {
          "type": "string"
        },
        "url": {
          "type": "string"
        }
      },
      "title": "Application",
      "required": [
        "id",
        "name",
        "platform",
        "subscribe_type",
        "icon",
        "url"
      ]
    },
    "ApplicationResponse": {
      "type": "object",
      "properties": {
        "windows": {
          "type": "array",
          "items": {
            "$ref": "#/definitions/Application"
          }
        },
        "mac": {
          "type": "array",
          "items": {
            "$ref": "#/definitions/Application"
          }
        },
        "linux": {
          "type": "array",
          "items": {
            "$ref": "#/definitions/Application"
          }
        },
        "android": {
          "type": "array",
          "items": {
            "$ref": "#/definitions/Application"
          }
        },
        "ios": {
          "type": "array",
          "items": {
            "$ref": "#/definitions/Application"
          }
        }
      },
      "title": "ApplicationResponse",
      "required": [
        "windows",
        "mac",
        "linux",
        "android",
        "ios"
      ]
    },
    "CheckUserRequest": {
      "type": "object",
      "properties": {
        "email": {
          "type": "string"
        }
      },
      "title": "CheckUserRequest",
      "required": [
        "email"
      ]
    },
    "CheckUserResponse": {
      "type": "object",
      "properties": {
        "exist": {
          "type": "boolean",
          "format": "boolean"
        }
      },
      "title": "CheckUserResponse",
      "required": [
        "exist"
      ]
    },
    "Coupon": {
      "type": "object",
      "properties": {
        "id": {
          "type": "integer",
          "format": "int64"
        },
        "name": {
          "type": "string"
        },
        "code": {
          "type": "string"
        },
        "count": {
          "type": "integer",
          "format": "int64"
        },
        "type": {
          "type": "integer",
          "format": "uint8"
        },
        "discount": {
          "type": "integer",
          "format": "int64"
        },
        "start_time": {
          "type": "integer",
          "format": "int64"
        },
        "expire_time": {
          "type": "integer",
          "format": "int64"
        },
        "user_limit": {
          "type": "integer",
          "format": "int64"
        },
        "subscribe": {
          "type": "array",
          "items": {
            "type": "integer",
            "format": "int64"
          }
        },
        "used_count": {
          "type": "integer",
          "format": "int64"
        },
        "enable": {
          "type": "boolean",
          "format": "boolean"
        },
        "created_at": {
          "type": "integer",
          "format": "int64"
        },
        "updated_at": {
          "type": "integer",
          "format": "int64"
        }
      },
      "title": "Coupon",
      "required": [
        "id",
        "name",
        "code",
        "count",
        "type",
        "discount",
        "start_time",
        "expire_time",
        "user_limit",
        "subscribe",
        "used_count",
        "enable",
        "created_at",
        "updated_at"
      ]
    },
    "CurrencyConfig": {
      "type": "object",
      "properties": {
        "currency_unit": {
          "type": "string"
        },
        "currency_symbol": {
          "type": "string"
        },
        "access_key": {
          "type": "string"
        }
      },
      "title": "CurrencyConfig",
      "required": [
        "currency_unit",
        "currency_symbol",
        "access_key"
      ]
    },
    "Document": {
      "type": "object",
      "properties": {
        "id": {
          "type": "integer",
          "format": "int64"
        },
        "title": {
          "type": "string"
        },
        "content": {
          "type": "string"
        },
        "tags": {
          "type": "array",
          "items": {
            "type": "string"
          }
        },
        "show": {
          "type": "boolean",
          "format": "boolean"
        },
        "created_at": {
          "type": "integer",
          "format": "int64"
        },
        "updated_at": {
          "type": "integer",
          "format": "int64"
        }
      },
      "title": "Document",
      "required": [
        "id",
        "title",
        "content",
        "tags",
        "show",
        "created_at",
        "updated_at"
      ]
    },
    "EmailSmtpConfig": {
      "type": "object",
      "properties": {
        "email_smtp_host": {
          "type": "string"
        },
        "email_smtp_port": {
          "type": "integer",
          "format": "int64"
        },
        "email_smtp_user": {
          "type": "string"
        },
        "email_smtp_pass": {
          "type": "string"
        },
        "email_smtp_from": {
          "type": "string"
        },
        "email_smtp_ssl": {
          "type": "boolean",
          "format": "boolean"
        },
        "verify_email_template": {
          "type": "string"
        },
        "maintenance_email_template": {
          "type": "string"
        },
        "expiration_email_template": {
          "type": "string"
        }
      },
      "title": "EmailSmtpConfig",
      "required": [
        "email_smtp_host",
        "email_smtp_port",
        "email_smtp_user",
        "email_smtp_pass",
        "email_smtp_from",
        "email_smtp_ssl",
        "verify_email_template",
        "maintenance_email_template",
        "expiration_email_template"
      ]
    },
    "Follow": {
      "type": "object",
      "properties": {
        "id": {
          "type": "integer",
          "format": "int64"
        },
        "ticket_id": {
          "type": "integer",
          "format": "int64"
        },
        "from": {
          "type": "string"
        },
        "type": {
          "type": "integer",
          "format": "uint8"
        },
        "content": {
          "type": "string"
        },
        "created_at": {
          "type": "integer",
          "format": "int64"
        }
      },
      "title": "Follow",
      "required": [
        "id",
        "ticket_id",
        "from",
        "type",
        "content",
        "created_at"
      ]
    },
    "GetGlobalConfigResponse": {
      "type": "object",
      "properties": {
        "site": {
          "$ref": "#/definitions/SiteConfig"
        },
        "verify": {
          "$ref": "#/definitions/VeifyConfig"
        },
        "register": {
          "$ref": "#/definitions/RegisterConfig"
        },
        "invite": {
          "$ref": "#/definitions/InviteConfig"
        },
        "currency": {
          "$ref": "#/definitions/CurrencyConfig"
        },
        "subscribe": {
          "$ref": "#/definitions/SubscribeConfig"
        }
      },
      "title": "GetGlobalConfigResponse",
      "required": [
        "site",
        "verify",
        "register",
        "invite",
        "currency",
        "subscribe"
      ]
    },
    "GetStatResponse": {
      "type": "object",
      "properties": {
        "user": {
          "type": "integer",
          "format": "int64"
        },
        "node": {
          "type": "integer",
          "format": "int64"
        },
        "country": {
          "type": "integer",
          "format": "int64"
        }
      },
      "title": "GetStatResponse",
      "required": [
        "user",
        "node",
        "country"
      ]
    },
    "GetSubscriptionResponse": {
      "type": "object",
      "properties": {
        "list": {
          "type": "array",
          "items": {
            "$ref": "#/definitions/Subscribe"
          }
        }
      },
      "title": "GetSubscriptionResponse",
      "required": [
        "list"
      ]
    },
    "GetTosResponse": {
      "type": "object",
      "properties": {
        "tos_content": {
          "type": "string"
        }
      },
      "title": "GetTosResponse",
      "required": [
        "tos_content"
      ]
    },
    "InviteConfig": {
      "type": "object",
      "properties": {
        "forced_invite": {
          "type": "boolean",
          "format": "boolean"
        },
        "referral_percentage": {
          "type": "integer",
          "format": "int64"
        },
        "only_first_purchase": {
          "type": "boolean",
          "format": "boolean"
        }
      },
      "title": "InviteConfig",
      "required": [
        "forced_invite",
        "referral_percentage",
        "only_first_purchase"
      ]
    },
    "LoginResponse": {
      "type": "object",
      "properties": {
        "token": {
          "type": "string"
        }
      },
      "title": "LoginResponse",
      "required": [
        "token"
      ]
    },
    "NodeConfig": {
      "type": "object",
      "properties": {
        "node_secret": {
          "type": "string"
        },
        "node_pull_interval": {
          "type": "integer",
          "format": "int64"
        },
        "node_push_interval": {
          "type": "integer",
          "format": "int64"
        }
      },
      "title": "NodeConfig",
      "required": [
        "node_secret",
        "node_pull_interval",
        "node_push_interval"
      ]
    },
    "Order": {
      "type": "object",
      "properties": {
        "id": {
          "type": "integer",
          "format": "int64"
        },
        "user_id": {
          "type": "integer",
          "format": "int64"
        },
        "order_no": {
          "type": "string"
        },
        "type": {
          "type": "integer",
          "format": "uint8"
        },
        "quantity": {
          "type": "integer",
          "format": "int64"
        },
        "price": {
          "type": "integer",
          "format": "int64"
        },
        "amount": {
          "type": "integer",
          "format": "int64"
        },
        "discount": {
          "type": "integer",
          "format": "int64"
        },
        "coupon": {
          "type": "string"
        },
        "coupon_discount": {
          "type": "integer",
          "format": "int64"
        },
        "method": {
          "type": "string"
        },
        "fee_amount": {
          "type": "integer",
          "format": "int64"
        },
        "trade_no": {
          "type": "string"
        },
        "status": {
          "type": "integer",
          "format": "uint8"
        },
        "subscribe_id": {
          "type": "integer",
          "format": "int64"
        },
        "created_at": {
          "type": "integer",
          "format": "int64"
        },
        "updated_at": {
          "type": "integer",
          "format": "int64"
        }
      },
      "title": "Order",
      "required": [
        "id",
        "user_id",
        "order_no",
        "type",
        "quantity",
        "price",
        "amount",
        "discount",
        "coupon",
        "coupon_discount",
        "method",
        "fee_amount",
        "trade_no",
        "status",
        "subscribe_id",
        "created_at",
        "updated_at"
      ]
    },
    "OrderDetail": {
      "type": "object",
      "properties": {
        "id": {
          "type": "integer",
          "format": "int64"
        },
        "user_id": {
          "type": "integer",
          "format": "int64"
        },
        "order_no": {
          "type": "string"
        },
        "type": {
          "type": "integer",
          "format": "uint8"
        },
        "quantity": {
          "type": "integer",
          "format": "int64"
        },
        "price": {
          "type": "integer",
          "format": "int64"
        },
        "amount": {
          "type": "integer",
          "format": "int64"
        },
        "discount": {
          "type": "integer",
          "format": "int64"
        },
        "coupon": {
          "type": "string"
        },
        "coupon_discount": {
          "type": "integer",
          "format": "int64"
        },
        "method": {
          "type": "string"
        },
        "fee_amount": {
          "type": "integer",
          "format": "int64"
        },
        "trade_no": {
          "type": "string"
        },
        "status": {
          "type": "integer",
          "format": "uint8"
        },
        "subscribe_id": {
          "type": "integer",
          "format": "int64"
        },
        "subscribe": {
          "$ref": "#/definitions/Subscribe"
        },
        "created_at": {
          "type": "integer",
          "format": "int64"
        },
        "updated_at": {
          "type": "integer",
          "format": "int64"
        }
      },
      "title": "OrderDetail",
      "required": [
        "id",
        "user_id",
        "order_no",
        "type",
        "quantity",
        "price",
        "amount",
        "discount",
        "coupon",
        "coupon_discount",
        "method",
        "fee_amount",
        "trade_no",
        "status",
        "subscribe_id",
        "subscribe",
        "created_at",
        "updated_at"
      ]
    },
    "PaymentConfig": {
      "type": "object",
      "properties": {
        "id": {
          "type": "integer",
          "format": "int64"
        },
        "name": {
          "type": "string"
        },
        "mark": {
          "type": "string"
        },
        "icon": {
          "type": "string"
        },
        "domain": {
          "type": "string"
        },
        "config": {
          "type": "object"
        },
        "fee_mode": {
          "type": "integer",
          "format": "uint32"
        },
        "fee_percent": {
          "type": "integer",
          "format": "int64"
        },
        "fee_amount": {
          "type": "integer",
          "format": "int64"
        },
        "enable": {
          "type": "boolean",
          "format": "boolean"
        }
      },
      "title": "PaymentConfig",
      "required": [
        "id",
        "name",
        "mark",
        "config",
        "fee_mode",
        "enable"
      ]
    },
    "Push": {
      "type": "object",
      "properties": {
        "push_at": {
          "type": "integer",
          "format": "int64"
        },
        "count": {
          "type": "integer",
          "format": "int32"
        }
      },
      "title": "Push",
      "required": [
        "push_at",
        "count"
      ]
    },
    "RegisterConfig": {
      "type": "object",
      "properties": {
        "stop_register": {
          "type": "boolean",
          "format": "boolean"
        },
        "enable_trial": {
          "type": "boolean",
          "format": "boolean"
        },
        "enable_email_verify": {
          "type": "boolean",
          "format": "boolean"
        },
        "enable_email_domain_suffix": {
          "type": "boolean",
          "format": "boolean"
        },
        "email_domain_suffix_list": {
          "type": "string"
        },
        "enable_ip_register_limit": {
          "type": "boolean",
          "format": "boolean"
        },
        "ip_register_limit": {
          "type": "integer",
          "format": "int64"
        },
        "ip_register_limit_duration": {
          "type": "integer",
          "format": "int64"
        }
      },
      "title": "RegisterConfig",
      "required": [
        "stop_register",
        "enable_trial",
        "enable_email_verify",
        "enable_email_domain_suffix",
        "email_domain_suffix_list",
        "enable_ip_register_limit",
        "ip_register_limit",
        "ip_register_limit_duration"
      ]
    },
    "ResetPasswordRequest": {
      "type": "object",
      "properties": {
        "email": {
          "type": "string"
        },
        "password": {
          "type": "string"
        },
        "code": {
          "type": "string"
        },
        "cf_token": {
          "type": "string"
        }
      },
      "title": "ResetPasswordRequest",
      "required": [
        "email",
        "password"
      ]
    },
    "Response": {
      "type": "object",
      "properties": {
        "code": {
          "type": "integer",
          "description": "状态码"
        },
        "msg": {
          "type": "string",
          "description": "消息"
        },
        "data": {
          "type": "object",
          "description": "数据"
        }
      }
    },
    "SendCodeRequest": {
      "type": "object",
      "properties": {
        "email": {
          "type": "string"
        },
        "type": {
          "type": "integer",
          "format": "uint8"
        }
      },
      "title": "SendCodeRequest",
      "required": [
        "email",
        "type"
      ]
    },
    "SendCodeResponse": {
      "type": "object",
      "properties": {
        "status": {
          "type": "boolean",
          "format": "boolean"
        }
      },
      "title": "SendCodeResponse",
      "required": [
        "status"
      ]
    },
    "Server": {
      "type": "object",
      "properties": {
        "id": {
          "type": "integer",
          "format": "int64"
        },
        "name": {
          "type": "string"
        },
        "server_addr": {
          "type": "string"
        },
        "speed_limit": {
          "type": "integer",
          "format": "int32"
        },
        "traffic_ratio": {
          "type": "number",
          "format": "float"
        },
        "groupId": {
          "type": "integer",
          "format": "int64"
        },
        "protocol": {
          "type": "string"
        },
        "enable": {
          "type": "boolean",
          "format": "boolean"
        },
        "vmess": {
          "$ref": "#/definitions/Vmess"
        },
        "vless": {
          "$ref": "#/definitions/Vless"
        },
        "trojan": {
          "$ref": "#/definitions/Trojan"
        },
        "shadowsocks": {
          "$ref": "#/definitions/Shadowsocks"
        },
        "created_at": {
          "type": "integer",
          "format": "int64"
        },
        "updated_at": {
          "type": "integer",
          "format": "int64"
        },
        "last": {
          "$ref": "#/definitions/Push"
        }
      },
      "title": "Server",
      "required": [
        "id",
        "name",
        "server_addr",
        "speed_limit",
        "traffic_ratio",
        "groupId",
        "protocol",
        "enable",
        "created_at",
        "updated_at",
        "last"
      ]
    },
    "ServerGroup": {
      "type": "object",
      "properties": {
        "id": {
          "type": "integer",
          "format": "int64"
        },
        "name": {
          "type": "string"
        },
        "description": {
          "type": "string"
        },
        "created_at": {
          "type": "integer",
          "format": "int64"
        },
        "updated_at": {
          "type": "integer",
          "format": "int64"
        }
      },
      "title": "ServerGroup",
      "required": [
        "id",
        "name",
        "description",
        "created_at",
        "updated_at"
      ]
    },
    "Shadowsocks": {
      "type": "object",
      "properties": {
        "method": {
          "type": "string"
        },
        "port": {
          "type": "integer",
          "format": "int32"
        },
        "enable_relay": {
          "type": "boolean",
          "format": "boolean"
        },
        "relay_host": {
          "type": "string"
        },
        "relay_port": {
          "type": "integer",
          "format": "int32"
        }
      },
      "title": "Shadowsocks",
      "required": [
        "method",
        "port",
        "enable_relay",
        "relay_host",
        "relay_port"
      ]
    },
    "SiteConfig": {
      "type": "object",
      "properties": {
        "host": {
          "type": "string"
        },
        "site_name": {
          "type": "string"
        },
        "site_desc": {
          "type": "string"
        },
        "site_logo": {
          "type": "string"
        }
      },
      "title": "SiteConfig",
      "required": [
        "host",
        "site_name",
        "site_desc",
        "site_logo"
      ]
    },
    "Subscribe": {
      "type": "object",
      "properties": {
        "id": {
          "type": "integer",
          "format": "int64"
        },
        "name": {
          "type": "string"
        },
        "description": {
          "type": "string"
        },
        "unit_price": {
          "type": "integer",
          "format": "int64"
        },
        "discount": {
          "type": "array",
          "items": {
            "$ref": "#/definitions/SubscribeDiscount"
          }
        },
        "replacement": {
          "type": "integer",
          "format": "int64"
        },
        "inventory": {
          "type": "integer",
          "format": "int64"
        },
        "traffic": {
          "type": "integer",
          "format": "int64"
        },
        "speed_limit": {
          "type": "integer",
          "format": "int64"
        },
        "device_limit": {
          "type": "integer",
          "format": "int64"
        },
        "quota": {
          "type": "integer",
          "format": "int64"
        },
        "group_id": {
          "type": "integer",
          "format": "int64"
        },
        "server_group": {
          "type": "array",
          "items": {
            "type": "integer",
            "format": "int64"
          }
        },
        "server": {
          "type": "array",
          "items": {
            "type": "integer",
            "format": "int64"
          }
        },
        "show": {
          "type": "boolean",
          "format": "boolean"
        },
        "sell": {
          "type": "boolean",
          "format": "boolean"
        },
        "created_at": {
          "type": "integer",
          "format": "int64"
        },
        "updated_at": {
          "type": "integer",
          "format": "int64"
        }
      },
      "title": "Subscribe",
      "required": [
        "id",
        "name",
        "description",
        "unit_price",
        "discount",
        "replacement",
        "inventory",
        "traffic",
        "speed_limit",
        "device_limit",
        "quota",
        "group_id",
        "server_group",
        "server",
        "show",
        "sell",
        "created_at",
        "updated_at"
      ]
    },
    "SubscribeConfig": {
      "type": "object",
      "properties": {
        "single_model": {
          "type": "boolean",
          "format": "boolean"
        },
        "subscribe_path": {
          "type": "string"
        },
        "subscribe_domain": {
          "type": "string"
        },
        "pan_domain": {
          "type": "boolean",
          "format": "boolean"
        }
      },
      "title": "SubscribeConfig",
      "required": [
        "single_model",
        "subscribe_path",
        "subscribe_domain",
        "pan_domain"
      ]
    },
    "SubscribeDiscount": {
      "type": "object",
      "properties": {
        "months": {
          "type": "integer",
          "format": "int64"
        },
        "discount": {
          "type": "integer",
          "format": "int64"
        }
      },
      "title": "SubscribeDiscount",
      "required": [
        "months",
        "discount"
      ]
    },
    "SubscribeGroup": {
      "type": "object",
      "properties": {
        "id": {
          "type": "integer",
          "format": "int64"
        },
        "name": {
          "type": "string"
        },
        "description": {
          "type": "string"
        },
        "created_at": {
          "type": "integer",
          "format": "int64"
        },
        "updated_at": {
          "type": "integer",
          "format": "int64"
        }
      },
      "title": "SubscribeGroup",
      "required": [
        "id",
        "name",
        "description",
        "created_at",
        "updated_at"
      ]
    },
    "SubscribeType": {
      "type": "object",
      "properties": {
        "subscribe_types": {
          "type": "array",
          "items": {
            "type": "string"
          }
        }
      },
      "title": "SubscribeType",
      "required": [
        "subscribe_types"
      ]
    },
    "TelegramConfig": {
      "type": "object",
      "properties": {
        "telegram_bot_token": {
          "type": "string"
        },
        "telegram_group_url": {
          "type": "string"
        },
        "telegram_notify": {
          "type": "boolean",
          "format": "boolean"
        }
      },
      "title": "TelegramConfig",
      "required": [
        "telegram_bot_token",
        "telegram_group_url",
        "telegram_notify"
      ]
    },
    "Ticket": {
      "type": "object",
      "properties": {
        "id": {
          "type": "integer",
          "format": "int64"
        },
        "title": {
          "type": "string"
        },
        "description": {
          "type": "string"
        },
        "user_id": {
          "type": "integer",
          "format": "int64"
        },
        "follow": {
          "type": "array",
          "items": {
            "$ref": "#/definitions/Follow"
          }
        },
        "status": {
          "type": "integer",
          "format": "uint8"
        },
        "created_at": {
          "type": "integer",
          "format": "int64"
        },
        "updated_at": {
          "type": "integer",
          "format": "int64"
        }
      },
      "title": "Ticket",
      "required": [
        "id",
        "title",
        "description",
        "user_id",
        "status",
        "created_at",
        "updated_at"
      ]
    },
    "TosConfig": {
      "type": "object",
      "properties": {
        "tos_content": {
          "type": "string"
        }
      },
      "title": "TosConfig",
      "required": [
        "tos_content"
      ]
    },
    "Trojan": {
      "type": "object",
      "properties": {
        "network": {
          "type": "string"
        },
        "port": {
          "type": "integer",
          "format": "int32"
        },
        "host": {
          "type": "string"
        },
        "sni": {
          "type": "string"
        },
        "allow_insecure": {
          "type": "boolean",
          "format": "boolean"
        },
        "transport": {
          "type": "object"
        },
        "enable_relay": {
          "type": "boolean",
          "format": "boolean"
        },
        "relay_host": {
          "type": "string"
        },
        "relay_port": {
          "type": "integer",
          "format": "int32"
        }
      },
      "title": "Trojan",
      "required": [
        "network",
        "port",
        "host",
        "sni",
        "allow_insecure",
        "transport",
        "enable_relay",
        "relay_host",
        "relay_port"
      ]
    },
    "User": {
      "type": "object",
      "properties": {
        "id": {
          "type": "integer",
          "format": "int64"
        },
        "email": {
          "type": "string"
        },
        "avatar": {
          "type": "string"
        },
        "balance": {
          "type": "integer",
          "format": "int64"
        },
        "telegram": {
          "type": "integer",
          "format": "int64"
        },
        "refer_code": {
          "type": "string"
        },
        "referer_id": {
          "type": "integer",
          "format": "int64"
        },
        "enable": {
          "type": "boolean",
          "format": "boolean"
        },
        "is_admin": {
          "type": "boolean",
          "format": "boolean"
        },
        "valid_email": {
          "type": "boolean",
          "format": "boolean"
        },
        "enable_email_notify": {
          "type": "boolean",
          "format": "boolean"
        },
        "enable_telegram_notify": {
          "type": "boolean",
          "format": "boolean"
        },
        "enable_balance_notify": {
          "type": "boolean",
          "format": "boolean"
        },
        "enable_login_notify": {
          "type": "boolean",
          "format": "boolean"
        },
        "enable_subscribe_notify": {
          "type": "boolean",
          "format": "boolean"
        },
        "enable_trade_notify": {
          "type": "boolean",
          "format": "boolean"
        },
        "created_at": {
          "type": "integer",
          "format": "int64"
        },
        "updated_at": {
          "type": "integer",
          "format": "int64"
        },
        "deleted_at": {
          "type": "integer",
          "format": "int64"
        },
        "is_del": {
          "type": "boolean",
          "format": "boolean"
        }
      },
      "title": "User",
      "required": [
        "id",
        "email",
        "avatar",
        "balance",
        "telegram",
        "refer_code",
        "referer_id",
        "enable",
        "valid_email",
        "enable_email_notify",
        "enable_telegram_notify",
        "enable_balance_notify",
        "enable_login_notify",
        "enable_subscribe_notify",
        "enable_trade_notify",
        "created_at",
        "updated_at"
      ]
    },
    "UserAffiliate": {
      "type": "object",
      "properties": {
        "email": {
          "type": "string"
        },
        "avatar": {
          "type": "string"
        },
        "registered_at": {
          "type": "integer",
          "format": "int64"
        },
        "enable": {
          "type": "boolean",
          "format": "boolean"
        }
      },
      "title": "UserAffiliate",
      "required": [
        "email",
        "avatar",
        "registered_at",
        "enable"
      ]
    },
    "UserBalanceLog": {
      "type": "object",
      "properties": {
        "id": {
          "type": "integer",
          "format": "int64"
        },
        "user_id": {
          "type": "integer",
          "format": "int64"
        },
        "amount": {
          "type": "integer",
          "format": "int64"
        },
        "type": {
          "type": "integer",
          "format": "uint8"
        },
        "order_id": {
          "type": "integer",
          "format": "int64"
        },
        "balance": {
          "type": "integer",
          "format": "int64"
        },
        "created_at": {
          "type": "integer",
          "format": "int64"
        }
      },
      "title": "UserBalanceLog",
      "required": [
        "id",
        "user_id",
        "amount",
        "type",
        "order_id",
        "balance",
        "created_at"
      ]
    },
    "UserLoginRequest": {
      "type": "object",
      "properties": {
        "email": {
          "type": "string"
        },
        "password": {
          "type": "string"
        },
        "cf_token": {
          "type": "string"
        }
      },
      "title": "UserLoginRequest",
      "required": [
        "email",
        "password"
      ]
    },
    "UserRegisterRequest": {
      "type": "object",
      "properties": {
        "email": {
          "type": "string"
        },
        "password": {
          "type": "string"
        },
        "invite": {
          "type": "string"
        },
        "code": {
          "type": "string"
        },
        "cf_token": {
          "type": "string"
        }
      },
      "title": "UserRegisterRequest",
      "required": [
        "email",
        "password"
      ]
    },
    "UserSubscribe": {
      "type": "object",
      "properties": {
        "id": {
          "type": "integer",
          "format": "int64"
        },
        "user_id": {
          "type": "integer",
          "format": "int64"
        },
        "order_id": {
          "type": "integer",
          "format": "int64"
        },
        "subscribe_id": {
          "type": "integer",
          "format": "int64"
        },
        "subscribe": {
          "$ref": "#/definitions/Subscribe"
        },
        "start_time": {
          "type": "integer",
          "format": "int64"
        },
        "expire_time": {
          "type": "integer",
          "format": "int64"
        },
        "traffic": {
          "type": "integer",
          "format": "int64"
        },
        "download": {
          "type": "integer",
          "format": "int64"
        },
        "upload": {
          "type": "integer",
          "format": "int64"
        },
        "mark": {
          "type": "string"
        },
        "status": {
          "type": "integer",
          "format": "uint8"
        },
        "created_at": {
          "type": "integer",
          "format": "int64"
        },
        "updated_at": {
          "type": "integer",
          "format": "int64"
        }
      },
      "title": "UserSubscribe",
      "required": [
        "id",
        "user_id",
        "order_id",
        "subscribe_id",
        "subscribe",
        "start_time",
        "expire_time",
        "traffic",
        "download",
        "upload",
        "mark",
        "status",
        "created_at",
        "updated_at"
      ]
    },
    "VeifyConfig": {
      "type": "object",
      "properties": {
        "turnstile_site_key": {
          "type": "string"
        },
        "enable_login_verify": {
          "type": "boolean",
          "format": "boolean"
        },
        "enable_register_verify": {
          "type": "boolean",
          "format": "boolean"
        },
        "enable_reset_password_verify": {
          "type": "boolean",
          "format": "boolean"
        }
      },
      "title": "VeifyConfig",
      "required": [
        "turnstile_site_key",
        "enable_login_verify",
        "enable_register_verify",
        "enable_reset_password_verify"
      ]
    },
    "VerifyConfig": {
      "type": "object",
      "properties": {
        "turnstile_site_key": {
          "type": "string"
        },
        "turnstile_secret": {
          "type": "string"
        },
        "enable_login_verify": {
          "type": "boolean",
          "format": "boolean"
        },
        "enable_register_verify": {
          "type": "boolean",
          "format": "boolean"
        },
        "enable_reset_password_verify": {
          "type": "boolean",
          "format": "boolean"
        }
      },
      "title": "VerifyConfig",
      "required": [
        "turnstile_site_key",
        "turnstile_secret",
        "enable_login_verify",
        "enable_register_verify",
        "enable_reset_password_verify"
      ]
    },
    "Vless": {
      "type": "object",
      "properties": {
        "host": {
          "type": "string"
        },
        "port": {
          "type": "integer",
          "format": "int32"
        },
        "network": {
          "type": "string"
        },
        "transport": {
          "type": "object"
        },
        "security": {
          "type": "string"
        },
        "security_config": {
          "type": "object"
        },
        "xtls": {
          "type": "string"
        },
        "enable_relay": {
          "type": "boolean",
          "format": "boolean"
        },
        "relay_host": {
          "type": "string"
        },
        "relay_port": {
          "type": "integer",
          "format": "int32"
        }
      },
      "title": "Vless",
      "required": [
        "host",
        "port",
        "network",
        "transport",
        "security",
        "security_config",
        "xtls",
        "enable_relay",
        "relay_host",
        "relay_port"
      ]
    },
    "Vmess": {
      "type": "object",
      "properties": {
        "host": {
          "type": "string"
        },
        "port": {
          "type": "integer",
          "format": "int32"
        },
        "enable_tls": {
          "type": "boolean",
          "format": "boolean"
        },
        "tls_config": {
          "type": "object"
        },
        "network": {
          "type": "string"
        },
        "transport": {
          "type": "object"
        },
        "enable_relay": {
          "type": "boolean",
          "format": "boolean"
        },
        "relay_host": {
          "type": "string"
        },
        "relay_port": {
          "type": "integer",
          "format": "int32"
        }
      },
      "title": "Vmess",
      "required": [
        "host",
        "port",
        "enable_tls",
        "tls_config",
        "network",
        "transport",
        "enable_relay",
        "relay_host",
        "relay_port"
      ]
    }
  },
  "securityDefinitions": {
    "apiKey": {
      "type": "apiKey",
      "description": "Enter JWT Bearer token **_only_**",
      "name": "Authorization",
      "in": "header"
    }
  }
}
